ali_ops/__init__.py
ali_ops/__main__.py
ali_ops/client/client.py
ali_ops/completors/customCompleter.py
ali_ops/completors/customRegionCompletor.py
ali_ops/config/config.py
ali_ops/decorators/logger.py
ali_ops/decorators/simple.py
ali_ops/decorators/singleton.py
ali_ops/decorators/test.py
ali_ops/decorators/timer.py
ali_ops/ecs/ecs.py
ali_ops/ecs/ecsImage.py
ali_ops/ecs/securityGroup.py
ali_ops/utils/debug.py
ali_ops/utils/utils.py
ali_ops/validators/validators.py
ali_ops/vpc/vpc.py
ali_ops/vpc/vswitch.py
ali_ops-1.0.16.dist-info/METADATA
ali_ops-1.0.16.dist-info/WHEEL
ali_ops-1.0.16.dist-info/entry_points.txt
ali_ops-1.0.16.dist-info/RECORD
