Metadata-Version: 2.4
Name: ali-ops
Version: 1.0.16
Summary: 阿里云命令行工具
Requires-Python: >=3.13
Requires-Dist: alibabacloud-ecs20140526>=7.2.0
Requires-Dist: alibabacloud-vpc20160428==6.11.9
Requires-Dist: fire>=0.7.0
Requires-Dist: prompt-toolkit>=3.0.51
Requires-Dist: pyperclip>=1.11.0
Requires-Dist: questionary>=2.1.0
Requires-Dist: toml>=0.10.2
